[
  {
    "title": "One Punch Man Anime_L2",
    "link_thumb": "https://live.staticflickr.com/65535/51787069926_06345a60a8_o.gif",
    "id_album": "-1626855613",
    "total": 2,
    "size_max_detail_page": 1,
    "list_detail": [
      {
        "index_page": 0,
        "link_page": "https://github.com/lmbstudiocontact/mb4_dt_alb_0/raw/main/14132021_dta_-1626855613_index_0.json"
      }
    ]
  },
  {
    "title": "Football_L9",
    "link_thumb": "https://live.staticflickr.com/65535/51787594904_d32bd03b6e_o.gif",
    "id_album": "-371026081",
    "total": 49,
    "size_max_detail_page": 1,
    "list_detail": [
      {
        "index_page": 0,
        "link_page": "https://github.com/lmbstudiocontact/mb4_dt_alb_0/raw/main/14132021_dta_-371026081_index_0.json"
      }
    ]
  },
  {
    "title": "Ragnarok_L3",
    "link_thumb": "https://live.staticflickr.com/65535/51787116701_8c9bf388b2_o.gif",
    "id_album": "1601322211",
    "total": 15,
    "size_max_detail_page": 1,
    "list_detail": [
      {
        "index_page": 0,
        "link_page": "https://github.com/lmbstudiocontact/mb4_dt_alb_0/raw/main/14132021_dta_1601322211_index_0.json"
      }
    ]
  },
  {
    "title": "Joker Harley Quinn_L8",
    "link_thumb": "https://live.staticflickr.com/65535/51786165377_1cfa864554_o.gif",
    "id_album": "-2022175630",
    "total": 24,
    "size_max_detail_page": 1,
    "list_detail": [
      {
        "index_page": 0,
        "link_page": "https://github.com/lmbstudiocontact/mb4_dt_alb_0/raw/main/14132021_dta_-2022175630_index_0.json"
      }
    ]
  },
  {
    "title": "Seven deadly sins Anime_L10",
    "link_thumb": "https://live.staticflickr.com/65535/51787360238_dc702fc071_o.gif",
    "id_album": "33964247",
    "total": 43,
    "size_max_detail_page": 1,
    "list_detail": [
      {
        "index_page": 0,
        "link_page": "https://github.com/lmbstudiocontact/mb4_dt_alb_0/raw/main/14132021_dta_33964247_index_0.json"
      }
    ]
  },
  {
    "title": "Seven deadly sins Anime_L8",
    "link_thumb": "https://live.staticflickr.com/65535/51787383943_f9530c1c58_o.gif",
    "id_album": "1802210944",
    "total": 43,
    "size_max_detail_page": 1,
    "list_detail": [
      {
        "index_page": 0,
        "link_page": "https://github.com/lmbstudiocontact/mb4_dt_alb_0/raw/main/14132021_dta_1802210944_index_0.json"
      }
    ]
  },
  {
    "title": "Dragon Art_L2",
    "link_thumb": "https://live.staticflickr.com/65535/51787567314_cca7762303_o.gif",
    "id_album": "2059013999",
    "total": 13,
    "size_max_detail_page": 1,
    "list_detail": [
      {
        "index_page": 0,
        "link_page": "https://github.com/lmbstudiocontact/mb4_dt_alb_0/raw/main/14132021_dta_2059013999_index_0.json"
      }
    ]
  },
  {
    "title": "Animal Art_L10",
    "link_thumb": "https://live.staticflickr.com/65535/51787169833_ca99ba0800_o.gif",
    "id_album": "-1287735957",
    "total": 7,
    "size_max_detail_page": 1,
    "list_detail": [
      {
        "index_page": 0,
        "link_page": "https://github.com/lmbstudiocontact/mb4_dt_alb_0/raw/main/14132021_dta_-1287735957_index_0.json"
      }
    ]
  },
  {
    "title": "Football_L3",
    "link_thumb": "https://live.staticflickr.com/65535/51787220053_bb602f2b58_o.gif",
    "id_album": "-371026087",
    "total": 25,
    "size_max_detail_page": 1,
    "list_detail": [
      {
        "index_page": 0,
        "link_page": "https://github.com/lmbstudiocontact/mb4_dt_alb_0/raw/main/14132021_dta_-371026087_index_0.json"
      }
    ]
  },
  {
    "title": "One Piece Anime_L3",
    "link_thumb": "https://live.staticflickr.com/65535/51787307103_12136cd0a8_o.gif",
    "id_album": "1351456606",
    "total": 135,
    "size_max_detail_page": 3,
    "list_detail": [
      {
        "index_page": 0,
        "link_page": "https://github.com/lmbstudiocontact/mb4_dt_alb_0/raw/main/14132021_dta_1351456606_index_0.json"
      },
      {
        "index_page": 1,
        "link_page": "https://github.com/lmbstudiocontact/mb4_dt_alb_0/raw/main/14132021_dta_1351456606_index_1.json"
      },
      {
        "index_page": 2,
        "link_page": "https://github.com/lmbstudiocontact/mb4_dt_alb_0/raw/main/14132021_dta_1351456606_index_2.json"
      }
    ]
  }
]